xpidy/__init__.py
xpidy/cli.py
xpidy/core/__init__.py
xpidy/core/config.py
xpidy/core/llm_processor.py
xpidy/core/spider.py
xpidy/extractors/__init__.py
xpidy/extractors/base_extractor.py
xpidy/extractors/data_extractor.py
xpidy/extractors/form_extractor.py
xpidy/extractors/image_extractor.py
xpidy/extractors/link_extractor.py
xpidy/extractors/text_extractor.py
xpidy/utils/__init__.py
xpidy/utils/cache.py
xpidy/utils/content_utils.py
xpidy/utils/proxy.py
xpidy/utils/retry.py
xpidy/utils/stats.py
xpidy/utils/url_utils.py
xpidy-0.2.0.dist-info/METADATA
xpidy-0.2.0.dist-info/WHEEL
xpidy-0.2.0.dist-info/entry_points.txt
xpidy-0.2.0.dist-info/RECORD
