Metadata-Version: 2.4
Name: xpidy
Version: 0.2.0
Summary: 一个基于 Playwright 和 LLM 的智能爬虫工具
Requires-Python: >=3.12
Requires-Dist: aiohttp>=3.9.0
Requires-Dist: anthropic>=0.21.0
Requires-Dist: beautifulsoup4>=4.12.0
Requires-Dist: click>=8.0.0
Requires-Dist: jinja2>=3.1.0
Requires-Dist: loguru>=0.7.0
Requires-Dist: openai>=1.0.0
Requires-Dist: playwright>=1.40.0
Requires-Dist: pydantic>=2.0.0
Provides-Extra: dev
Requires-Dist: black>=23.0.0; extra == 'dev'
Requires-Dist: isort>=5.12.0; extra == 'dev'
Requires-Dist: mypy>=1.0.0; extra == 'dev'
Requires-Dist: pytest-asyncio>=0.21.0; extra == 'dev'
Requires-Dist: pytest-cov>=4.0.0; extra == 'dev'
Requires-Dist: pytest-mock>=3.0.0; extra == 'dev'
Requires-Dist: pytest>=7.0.0; extra == 'dev'
